Workbook

Sheet Data
A1: Dynamic Sales Analytics Dashboard | H1: Jyothi Indira Priya Dharshini
A20: Date | B20: Region | C20: Salesperson | D20: Product | E20: Quantity Sold | F20: Sales Amount | G20: Discount (%) | H20: Profit Margin (%) | I20: Month | J20: Total Sales amount | K20: Total Sales | L20: Profit Amount | M20: Net Sales Amount | N20: Profit after Discount
A21: 45292 | B21: East | C21: Arun Kumar | D21: Product X | E21: 150 | F21: 3000 | G21: 10 | H21: 20 | I21: =TEXT(A21,"mmm") -> Jan | J21: 450000 | K21: {=E21:E110*F21:F110} -> 450000 | L21: =F21*(H21/100) -> 600 | M21: =F21-(F21*G21/100) -> 2700 | N21: =M21*(H21/100) -> 540
A22: 45293 | B22: West | C22: Priya Sharma | D22: Product Y | E22: 200 | F22: 4000 | G22: 15 | H22: 25 | I22: =TEXT(A22,"mmm") -> Jan | J22: 800000 | K22: 800000 | L22: =F22*(H22/100) -> 1000 | M22: =F22-(F22*G22/100) -> 3400 | N22: =M22*(H22/100) -> 850
A23: 45294 | B23: North | C23: Rajesh Patel | D23: Product X | E23: 120 | F23: 2400 | G23: 5 | H23: 18 | I23: =TEXT(A23,"mmm") -> Jan | J23: 288000 | K23: 288000 | L23: =F23*(H23/100) -> 432 | M23: =F23-(F23*G23/100) -> 2280 | N23: =M23*(H23/100) -> 410.4
A24: 45295 | B24: South | C24: Meera Reddy | D24: Product Z | E24: 250 | F24: 5000 | G24: 20 | H24: 30 | I24: =TEXT(A24,"mmm") -> Jan | J24: 1250000 | K24: 1250000 | L24: =F24*(H24/100) -> 1500 | M24: =F24-(F24*G24/100) -> 4000 | N24: =M24*(H24/100) -> 1200
A25: 45296 | B25: East | C25: Arun Kumar | D25: Product Y | E25: 100 | F25: 2000 | G25: 10 | H25: 22 | I25: =TEXT(A25,"mmm") -> Jan | J25: 200000 | K25: 200000 | L25: =F25*(H25/100) -> 440 | M25: =F25-(F25*G25/100) -> 1800 | N25: =M25*(H25/100) -> 396
A26: 45297 | B26: West | C26: Priya Sharma | D26: Product X | E26: 180 | F26: 3600 | G26: 12 | H26: 19 | I26: =TEXT(A26,"mmm") -> Jan | J26: 648000 | K26: 648000 | L26: =F26*(H26/100) -> 684 | M26: =F26-(F26*G26/100) -> 3168 | N26: =M26*(H26/100) -> 601.92
A27: 45298 | B27: North | C27: Rajesh Patel | D27: Product Y | E27: 150 | F27: 3000 | G27: 8 | H27: 21 | I27: =TEXT(A27,"mmm") -> Jan | J27: 450000 | K27: 450000 | L27: =F27*(H27/100) -> 630 | M27: =F27-(F27*G27/100) -> 2760 | N27: =M27*(H27/100) -> 579.6
A28: 45299 | B28: South | C28: Meera Reddy | D28: Product X | E28: 200 | F28: 4000 | G28: 15 | H28: 27 | I28: =TEXT(A28,"mmm") -> Jan | J28: 800000 | K28: 800000 | L28: =F28*(H28/100) -> 1080 | M28: =F28-(F28*G28/100) -> 3400 | N28: =M28*(H28/100) -> 918
A29: 45300 | B29: East | C29: Arun Kumar | D29: Product Z | E29: 170 | F29: 3400 | G29: 18 | H29: 23 | I29: =TEXT(A29,"mmm") -> Jan | J29: 578000 | K29: 578000 | L29: =F29*(H29/100) -> 782 | M29: =F29-(F29*G29/100) -> 2788 | N29: =M29*(H29/100) -> 641.24
A30: 45301 | B30: West | C30: Priya Sharma | D30: Product Z | E30: 130 | F30: 2600 | G30: 10 | H30: 20 | I30: =TEXT(A30,"mmm") -> Jan | J30: 338000 | K30: 338000 | L30: =F30*(H30/100) -> 520 | M30: =F30-(F30*G30/100) -> 2340 | N30: =M30*(H30/100) -> 468
A31: 45302 | B31: North | C31: Rajesh Patel | D31: Product X | E31: 160 | F31: 3200 | G31: 5 | H31: 22 | I31: =TEXT(A31,"mmm") -> Jan | J31: 512000 | K31: 512000 | L31: =F31*(H31/100) -> 704 | M31: =F31-(F31*G31/100) -> 3040 | N31: =M31*(H31/100) -> 668.8
A32: 45303 | B32: South | C32: Meera Reddy | D32: Product Y | E32: 180 | F32: 3600 | G32: 12 | H32: 25 | I32: =TEXT(A32,"mmm") -> Jan | J32: 648000 | K32: 648000 | L32: =F32*(H32/100) -> 900 | M32: =F32-(F32*G32/100) -> 3168 | N32: =M32*(H32/100) -> 792
A33: 45304 | B33: East | C33: Arun Kumar | D33: Product Y | E33: 140 | F33: 2800 | G33: 11 | H33: 24 | I33: =TEXT(A33,"mmm") -> Jan | J33: 392000 | K33: 392000 | L33: =F33*(H33/100) -> 672 | M33: =F33-(F33*G33/100) -> 2492 | N33: =M33*(H33/100) -> 598.08
... A110: 45382 | B110: South | C110: Meera Reddy | D110: Product Y | E110: 180 | F110: 3600 | G110: 17 | H110: 28 | I110: =TEXT(A110,"mmm") -> Mar | J110: 648000 | K110: 648000 | L110: =F110*(H110/100) -> 1008 | M110: =F110-(F110*G110/100) -> 2988 | N110: =M110*(H110/100) -> 836.64

Sheet Pivot Tables
B1: Pivot Tables For Graphs in Dashboard
A2: Product and Sales Amount | D2: Date and Quantity Sold | G2: Dates and Sales Amount
A3: Row Labels | B3: Sum of Sales Amount | D3: Row Labels | E3: Sum of Quantity Sold | G3: Row Labels | H3: Sum of Sales Amount
A4: Product X | B4: 88200 | D4: Jan | E4: 4980 | G4: Jan | H4: 99600
A5: Product Y | B5: 103400 | D5: Feb | E5: 4820 | G5: Feb | H5: 96400
A6: Product Z | B6: 110600 | D6: Mar | E6: 5310 | G6: Mar | H6: 106200
A7: Grand Total | B7: 302200 | D7: Grand Total | E7: 15110 | G7: Grand Total | H7: 302200
A9: Region and Total Sales | D9: Region and Quantity Sold | G9: Sales Person and Profit Margin
A10: Row Labels | B10: Sum of Total Sales Amount | D10: Row Labels | E10: Sum of Quantity Sold | G10: Row Labels | H10: Sum of Profit Margin (%)
A11: East | B11: 11466000 | D11: East | E11: 3570 | G11: Arun Kumar | H11: 532
A12: North | B12: 12568000 | D12: North | E12: 3660 | G12: Meera Reddy | H12: 598
A13: South | B13: 16472000 | D13: South | E13: 4200 | G13: Priya Sharma | H13: 524
A14: West | B14: 12020000 | D14: West | E14: 3680 | G14: Rajesh Patel | H14: 494
A15: Grand Total | B15: 52526000 | D15: Grand Total | E15: 15110 | G15: Grand Total | H15: 2148
A17: Product and Sales Amount | D17: Product and Quantity Sold | G17: Region,Date and Quantity Sold
A18: Row Labels | B18: Sum of Sales Amount | D18: Row Labels | E18: Sum of Quantity Sold | G18: Row Labels | H18: Sum of Quantity Sold
A19: Product X | B19: 88200 | D19: Product X | E19: 4410 | G19: East | H19: 3570
A20: Product Y | B20: 103400 | D20: Product Y | E20: 5170 | G20: North | H20: 3660
A21: Product Z | B21: 110600 | D21: Product Z | E21: 5530 | G21: South | H21: 4200
A22: Grand Total | B22: 302200 | D22: Grand Total | E22: 15110 | G22: West | H22: 3680
G23: Grand Total | H23: 15110
A24: Date (month) and Sales Amount
A25: Row Labels | B25: Sum of Sales Amount | D25: Sales Amount and Product
A26: Jan | B26: 99600 | E26: Column Labels
A27: Feb | B27: 96400 | E27: Product X | F27: Product Y | G27: Product Z | H27: Grand Total
A28: Mar | B28: 106200 | D28: Sum of Sales Amount | E28: 88200 | F28: 103400 | G28: 110600 | H28: 302200
A29: Grand Total | B29: 302200
A31: Product and Profit Margin
A32: Row Labels | B32: Sum of Profit Margin (%)
A33: Product X | B33: 647
A34: Product Y | B34: 752
A35: Product Z | B35: 749
A36: Grand Total | B36: 2148

Sheet Dashboard
E1: Dynamic Sales Analytics Dashboard | O1: By:J.Indira Priya Dharshini
A5: Max Quantity Sold And it's Month | E5: Highest Sold Product | J5: Region With Highest total sales amount | O5: Sales Person with Highest Sales Amount
A8: =MAX('Pivot Tables'!E4:E6) -> 5310 | E8: =_xlfn.XLOOKUP(MAX(Data!F21:F110),Data!F21:F110,Data!D21:D110,"No Product",0,1) -> Product Z | J8: =_xlfn.XLOOKUP(MAX(Data!J21:J110),Data!J21:J110,Data!B21:B110,"No such Region",0,1) -> South | O8: =_xlfn.XLOOKUP(MAX(Data!F21:F110),Data!F21:F110,Data!C21:C110,"No one",0,1) -> Meera Reddy
A10: =_xlfn.XLOOKUP(MAX('Pivot Tables'!E4:E6),'Pivot Tables'!E4:E6,'Pivot Tables'!D4:D6,"No Such Month",0,1) -> Mar
